{
  "sourceId": "src-santa-clara-fire-faq",
  "scopeType": "inspection_prep",
  "scopeKey": "santa-clara-fire-inspection",
  "sourceTier": "tier_1",
  "agency": "City of Santa Clara Fire Department",
  "title": "Fire Department FAQs",
  "sourceUrl": "https://www.santaclaraca.gov/our-city/departments-a-f/fire-department/faq-s",
  "quoteSummary": "Santa Clara says most new businesses are inspected within 30 days of the business license application and directs operators to call 408-615-4970 if they need to schedule the inspection.",
  "verifiedOn": "2026-04-07",
  "nextReviewOn": "2026-08-07"
}
